LICENSE
README.md
iplocbuild/__init__.py
iplocbuild/cli.py
iplocbuild-1.1.0.dist-info/LICENSE
iplocbuild-1.1.0.dist-info/METADATA
iplocbuild-1.1.0.dist-info/WHEEL
iplocbuild-1.1.0.dist-info/entry_points.txt
iplocbuild-1.1.0.dist-info/RECORD
