Metadata-Version: 2.1
Name: iplocbuild
Version: 1.1.0
Summary: Command line too to generate IP Location files from routes found on network devices.
Home-page: https://github.com/robwdwd/iplocbuild
License: BSD-2-Clause
Author: Rob Woodward
Author-email: rob@emailplus.org
Requires-Python: >=3.9,<4.0
Classifier: License :: OSI Approved :: BSD License
Classifier: Programming Language :: Python :: 3
Classifier: Programming Language :: Python :: 3.9
Classifier: Programming Language :: Python :: 3.10
Classifier: Programming Language :: Python :: 3.11
Requires-Dist: click (>=8.1.0,<9.0.0)
Requires-Dist: junos-eznc (>=2.6.3,<3.0.0)
Requires-Dist: lxml (>=4.6.5,<5.0.0)
Requires-Dist: netaddr (>=0.8.0,<0.9.0)
Project-URL: Repository, https://github.com/robwdwd/iplocbuild
